pytorch_visualizer/__init__.py
pytorch_visualizer/components_generator_functions.py
pytorch_visualizer/constants.py
pytorch_visualizer/demo.py
pytorch_visualizer/draw_on_screen.py
pytorch_visualizer/generate_coordinates.py
pytorch_visualizer/generate_objs_and_components.py
pytorch_visualizer/generators_and_utility_functions.py
pytorch_visualizer/initialization_funcs.py
pytorch_visualizer/main.py
pytorch_visualizer/minor_components.py
pytorch_visualizer/nn_visualizer.py
pytorch_visualizer/onclick_listeners.py
pytorch_visualizer/onclick_listeners_utility_funcs.py
pytorch_visualizer/parameters.py
pytorch_visualizer/persistent_vars.py
pytorch_visualizer/pytorch_prepare_for_visualization.py
pytorch_visualizer/screen_components.py
pytorch_visualizer/screen_operations.py
pytorch_visualizer/screen_state.py
pytorch_visualizer/scroll_screen.py
pytorch_visualizer/font/ARIAL.TTF
pytorch_visualizer-0.1.2.dist-info/LICENSE
pytorch_visualizer-0.1.2.dist-info/METADATA
pytorch_visualizer-0.1.2.dist-info/WHEEL
pytorch_visualizer-0.1.2.dist-info/top_level.txt
pytorch_visualizer-0.1.2.dist-info/RECORD
