Metadata-Version: 2.1
Name: pytorch_visualizer
Version: 0.1.2
Summary: A neural network visualization engine, built for pytorch
Home-page: https://github.com/Tony-Ale/pytorch_visualizer
Author: Oluwaseun Ale-Alaba
Author-email: carmichael8821@gmail.com
Classifier: Programming Language :: Python :: 3
Classifier: License :: OSI Approved :: MIT License
Classifier: Operating System :: OS Independent
Requires-Python: >=3.6
License-File: LICENSE
Requires-Dist: numpy >=1.26.4
Requires-Dist: pygame >=2.6.0
Requires-Dist: torch >=2.3.1
